django_scooby_profiler-2.0.7.dist-info/DESCRIPTION.rst
django_scooby_profiler-2.0.7.dist-info/METADATA
django_scooby_profiler-2.0.7.dist-info/RECORD
django_scooby_profiler-2.0.7.dist-info/WHEEL
django_scooby_profiler-2.0.7.dist-info/metadata.json
django_scooby_profiler-2.0.7.dist-info/top_level.txt
scooby/__init__.py
scooby/apps.py
scooby/backends.py
scooby/base.py
scooby/middleware.py
scooby/plugins_base.py
scooby/plugins_finder.py
scooby/settings.py
scooby/urls.py
scooby/utils.py
scooby/views.py
scooby/plugins/__init__.py
scooby/plugins/customlog/__init__.py
scooby/plugins/customlog/plugin.py
scooby/plugins/memcache/__init__.py
scooby/plugins/memcache/plugin.py
scooby/plugins/processtime/__init__.py
scooby/plugins/processtime/plugin.py
scooby/plugins/sql/__init__.py
scooby/plugins/sql/plugin.py
scooby/plugins/thriftpy/__init__.py
scooby/plugins/thriftpy/plugin.py
scooby/plugins/viewname/__init__.py
scooby/plugins/viewname/plugin.py
